{
  "Accept-Ranges": "bytes",
  "Connection": "Keep-Alive",
  "Content-Encoding": "gzip",
  "Content-Type": "application/xml",
  "Date": "Mon, 04 Sep 2017 13:47:41 GMT",
  "ETag": "\"2de444-5584c2250c66c-gzip\"",
  "Keep-Alive": "timeout=5, max=98",
  "Last-Modified": "Sun, 03 Sep 2017 17:15:00 GMT",
  "Server": "Apache",
  "Strict-Transport-Security": "max-age=31536000; includeSubDomains",
  "Transfer-Encoding": "chunked",
  "Vary": "Accept-Encoding",
  "Via": "1.1 f-droid.org (Apache/2.4.25)"
}