{
  "Accept-Ranges": "bytes",
  "Age": "1619",
  "Connection": "Keep-Alive",
  "Content-Encoding": "gzip",
  "Content-Length": "1039827",
  "Content-Type": "application/xml",
  "Date": "Tue, 04 Apr 2017 22:02:15 GMT",
  "ETag": "\"4709e1-54c508bd9011a-gzip\"",
  "Keep-Alive": "timeout=5, max=98",
  "Last-Modified": "Tue, 04 Apr 2017 05:28:30 GMT",
  "Server": "Apache",
  "Strict-Transport-Security": "max-age=31536000; includeSubDomains",
  "Vary": "Accept-Encoding",
  "Via": "1.1 f-droid.org (Apache/2.2.22)"
}