{
  "Accept-Ranges": "bytes",
  "Connection": "Keep-Alive",
  "Content-Encoding": "gzip",
  "Content-Type": "application/xml",
  "Date": "Tue, 25 Jul 2017 04:25:19 GMT",
  "ETag": "\"87a82e-5550132ee2df3-gzip\"",
  "Keep-Alive": "timeout=5, max=90",
  "Last-Modified": "Sun, 23 Jul 2017 19:35:21 GMT",
  "Server": "Apache",
  "Strict-Transport-Security": "max-age=31536000; includeSubDomains",
  "Transfer-Encoding": "chunked",
  "Vary": "Accept-Encoding",
  "Via": "1.1 f-droid.org (Apache/2.4.10)"
}