{
  "Accept-Ranges": "bytes",
  "Connection": "Keep-Alive",
  "Content-Encoding": "gzip",
  "Content-Type": "application/xml",
  "Date": "Fri, 02 Jun 2017 17:35:46 GMT",
  "ETag": "\"65b484-550f7ed470d28-gzip\"",
  "Keep-Alive": "timeout=5, max=90",
  "Last-Modified": "Fri, 02 Jun 2017 10:50:51 GMT",
  "Server": "Apache",
  "Strict-Transport-Security": "max-age=31536000; includeSubDomains",
  "Transfer-Encoding": "chunked",
  "Vary": "Accept-Encoding",
  "Via": "1.1 f-droid.org (Apache/2.4.10)"
}